kedro_dataframe_dropin/__init__.py
kedro_dataframe_dropin/core.py
kedro_dataframe_dropin/dask.py
kedro_dataframe_dropin/dask_rapids.py
kedro_dataframe_dropin/modin.py
kedro_dataframe_dropin/rapids.py
kedro_dataframe_dropin-0.2.0.dist-info/LICENSE.md
kedro_dataframe_dropin-0.2.0.dist-info/WHEEL
kedro_dataframe_dropin-0.2.0.dist-info/METADATA
kedro_dataframe_dropin-0.2.0.dist-info/RECORD
