Metadata-Version: 2.1
Name: kedro-dataframe-dropin
Version: 0.2.0
Summary: A Kedro plugin to utilise pandas dropins (like cuDF or modin) in place of the pandas datasets
Home-page: https://github.com/mzjp2/kedro-dataframe-dropin
License: MIT
Keywords: kedro,rapids,data,gpu,modin
Author: Zain Patel
Author-email: zain.patel06@gmail.com
Requires-Python: >=3.7.1,<3.9
Classifier: Framework :: Kedro
Classifier: License :: OSI Approved :: MIT License
Classifier: Programming Language :: Python :: 3
Classifier: Programming Language :: Python :: 3.8
Requires-Dist: kedro (>=0.17.0,<0.18.0)
Requires-Dist: pandas (>=1.0,<2.0)
Project-URL: Repository, https://github.com/mzjp2/kedro-dataframe-dropin
